stixdcpy/__init__.py
stixdcpy/algorithms.py
stixdcpy/auxiliary.py
stixdcpy/cfl.py
stixdcpy/continuous_spectrogram.py
stixdcpy/detector_view.py
stixdcpy/energylut.py
stixdcpy/housekeeping.py
stixdcpy/imgspec.py
stixdcpy/instrument.py
stixdcpy/io.py
stixdcpy/logger.py
stixdcpy/net.py
stixdcpy/quicklook.py
stixdcpy/science.py
stixdcpy/spectrogram.py
stixdcpy/stix_map.py
stixdcpy/time_util.py
stixdcpy/transmission.py
stixdcpy/utils.py
stixdcpy-3.0.dist-info/LICENSE.md
stixdcpy-3.0.dist-info/METADATA
stixdcpy-3.0.dist-info/WHEEL
stixdcpy-3.0.dist-info/top_level.txt
stixdcpy-3.0.dist-info/RECORD
