Metadata-Version: 2.1
Name: stixdcpy
Version: 3.0
Summary: STIX data center APIs and data analysis tools
Home-page: https://github.com/i4ds/stixdcpy
Author: Hualin Xiao
Author-email: hualin.xiao@fhnw.ch
License: UNKNOWN
Platform: UNKNOWN
Requires-Python: >=3.7
License-File: LICENSE.md
Requires-Dist: astropy
Requires-Dist: ipython
Requires-Dist: joblib
Requires-Dist: matplotlib
Requires-Dist: numpy
Requires-Dist: pandas
Requires-Dist: python-dateutil
Requires-Dist: requests
Requires-Dist: roentgen
Requires-Dist: simplejson
Requires-Dist: sunpy
Requires-Dist: tqdm
Requires-Dist: wget
